krakatoa/__init__.py
krakatoa/future/__init__.py
krakatoa/future/analysis.py
krakatoa/future/evaluate.py
krakatoa/future/experiment.py
krakatoa/future/preprocess.py
krakatoa/models/__init__.py
krakatoa/models/_config.py
krakatoa/models/_getmodels.py
krakatoa/models/_metrics.py
krakatoa/models/autotune.py
krakatoa/models/quick.py
krakatoa-0.0.7.dist-info/LICENSE
krakatoa-0.0.7.dist-info/METADATA
krakatoa-0.0.7.dist-info/WHEEL
krakatoa-0.0.7.dist-info/top_level.txt
krakatoa-0.0.7.dist-info/RECORD
