Metadata-Version: 2.1
Name: krakatoa
Version: 0.0.7
Summary: Machine Learning high level package.
Home-page: https://github.com/aitec-mp/krakatoa
Download-URL: https://github.com/aitec-mp/krakatoa/archive/refs/tags/0.0.7.tar.gz
Author: Matheus de Prá Andrade
Author-email: mpandrade@ucs.br
License: MIT
Keywords: krakatoa,machine learning
Classifier: Development Status :: 3 - Alpha
Classifier: Intended Audience :: Developers
Classifier: Topic :: Software Development :: Build Tools
Classifier: License :: OSI Approved :: MIT License
Classifier: Programming Language :: Python :: 3.7
Classifier: Programming Language :: Python :: 3.8
Classifier: Programming Language :: Python :: 3.9
Classifier: Programming Language :: Python :: 3.10
Classifier: Programming Language :: Python :: 3.11
License-File: LICENSE
Requires-Dist: scikit-learn
Requires-Dist: numpy
Requires-Dist: pandas
Requires-Dist: xgboost
Requires-Dist: seaborn
